valclient/__init__.py
valclient/auth.py
valclient/client.py
valclient/exceptions.py
valclient/resources.py
valclient_remake-2.28.dist-info/LICENSE
valclient_remake-2.28.dist-info/METADATA
valclient_remake-2.28.dist-info/WHEEL
valclient_remake-2.28.dist-info/top_level.txt
valclient_remake-2.28.dist-info/RECORD
