Metadata-Version: 2.1
Name: valclient-remake
Version: 2.28
Summary: Wrapper for VALORANT's client API
Home-page: https://github.com/mbok1200/valclient-2.28
Author: colinh
License: UNKNOWN
Platform: UNKNOWN
Classifier: Programming Language :: Python :: 3
Classifier: License :: OSI Approved :: MIT License
Classifier: Operating System :: OS Independent
Requires-Python: >=3.0
License-File: LICENSE
